Krira_Chunker/__init__.py
Krira_Chunker/config.py
Krira_Chunker/core.py
Krira_Chunker/exceptions.py
Krira_Chunker/router.py
Krira_Chunker/setup.py
Krira_Chunker/CSVChunker/__init__.py
Krira_Chunker/CSVChunker/csv_chunker.py
Krira_Chunker/DOCXChunker/__init__.py
Krira_Chunker/DOCXChunker/docx_chunker.py
Krira_Chunker/JSON_JSONLChunker/__init__.py
Krira_Chunker/JSON_JSONLChunker/json_chunker.py
Krira_Chunker/PDFChunker/__init__.py
Krira_Chunker/PDFChunker/pdf_chunker.py
Krira_Chunker/TextChunker/__init__.py
Krira_Chunker/TextChunker/text_chunker.py
Krira_Chunker/URLChunker/__init__.py
Krira_Chunker/URLChunker/url_chunker.py
Krira_Chunker/XLSXChunker/__init__.py
Krira_Chunker/XLSXChunker/xlsx_chunker.py
Krira_Chunker/XMLChunker/__init__.py
Krira_Chunker/XMLChunker/xml_chunker.py
Krira_Chunker/bench/__init__.py
Krira_Chunker/bench/__main__.py
Krira_Chunker/bench/runner.py
krira_chunker-0.2.0.dist-info/licenses/LICENSE
krira_chunker-0.2.0.dist-info/METADATA
krira_chunker-0.2.0.dist-info/WHEEL
krira_chunker-0.2.0.dist-info/entry_points.txt
krira_chunker-0.2.0.dist-info/top_level.txt
krira_chunker-0.2.0.dist-info/RECORD
