Metadata-Version: 2.4
Name: krira-chunker
Version: 0.2.0
Summary: Production-grade document chunking library for RAG applications
Home-page: https://github.com/kriralabs/krira-chunker
Author: Krira Labs
Author-email: Krira Labs <kriralabs@gmail.com>
Project-URL: Homepage, https://github.com/kriralabs/krira-chunker
Project-URL: Bug Tracker, https://github.com/kriralabs/krira-chunker/issues
Classifier: Development Status :: 4 - Beta
Classifier: Intended Audience :: Developers
Classifier: License :: OSI Approved :: MIT License
Classifier: Operating System :: OS Independent
Classifier: Programming Language :: Python :: 3
Classifier: Programming Language :: Python :: 3.10
Classifier: Programming Language :: Python :: 3.11
Classifier: Programming Language :: Python :: 3.12
Classifier: Topic :: Text Processing
Classifier: Topic :: Scientific/Engineering :: Artificial Intelligence
Requires-Python: >=3.10
License-File: LICENSE
Provides-Extra: pdf
Requires-Dist: pypdf>=4.0.0; extra == "pdf"
Provides-Extra: url
Requires-Dist: requests>=2.28.0; extra == "url"
Requires-Dist: beautifulsoup4>=4.12.0; extra == "url"
Requires-Dist: trafilatura>=1.6.0; extra == "url"
Provides-Extra: csv
Requires-Dist: polars>=0.20.0; extra == "csv"
Provides-Extra: xlsx
Requires-Dist: openpyxl>=3.1.0; extra == "xlsx"
Provides-Extra: json
Requires-Dist: ijson>=3.2.0; extra == "json"
Provides-Extra: tokens
Requires-Dist: tiktoken>=0.5.0; extra == "tokens"
Provides-Extra: test
Requires-Dist: pytest>=7.0.0; extra == "test"
Requires-Dist: pytest-asyncio>=0.21.0; extra == "test"
Requires-Dist: hypothesis>=6.0.0; extra == "test"
Provides-Extra: bench
Requires-Dist: psutil>=5.9.0; extra == "bench"
Requires-Dist: rich>=13.0.0; extra == "bench"
Provides-Extra: all
Requires-Dist: pypdf>=4.0.0; extra == "all"
Requires-Dist: requests>=2.28.0; extra == "all"
Requires-Dist: beautifulsoup4>=4.12.0; extra == "all"
Requires-Dist: trafilatura>=1.6.0; extra == "all"
Requires-Dist: polars>=0.20.0; extra == "all"
Requires-Dist: openpyxl>=3.1.0; extra == "all"
Requires-Dist: ijson>=3.2.0; extra == "all"
Requires-Dist: tiktoken>=0.5.0; extra == "all"
Requires-Dist: psutil>=5.9.0; extra == "all"
Requires-Dist: rich>=13.0.0; extra == "all"
Requires-Dist: pytest>=7.0.0; extra == "all"
Dynamic: author
Dynamic: home-page
Dynamic: license-file
Dynamic: requires-python
